MainframeLibrary.py
robotframework_mainframelibrary-1.0.0.dist-info/LICENSE
robotframework_mainframelibrary-1.0.0.dist-info/METADATA
robotframework_mainframelibrary-1.0.0.dist-info/WHEEL
robotframework_mainframelibrary-1.0.0.dist-info/top_level.txt
robotframework_mainframelibrary-1.0.0.dist-info/RECORD
