Metadata-Version: 2.1
Name: robotframework-mainframelibrary
Version: 1.0.0
Summary: Robot Framework Library for Mainframe
Home-page: https://github.com/NadezhdaBaranova/robotframework-mainframelibrary
Author: Nadezhda Baranova
License: UNKNOWN
Platform: UNKNOWN
Classifier: Programming Language :: Python :: 3
Classifier: License :: OSI Approved :: MIT License
Classifier: Operating System :: OS Independent
